{
    "Ar36": {
        "error": 2.6462133264660114e-07,
        "error_type": "",
        "fit": "previous",
        "references": [
            {
                "exclude": false,
                "record_id": "ba-01-n-15170"
            }
        ],
        "value": -8.193438118600516e-08
    },
    "Ar37": {
        "error": 2.2543098650474077e-07,
        "error_type": "",
        "fit": "previous",
        "references": [
            {
                "exclude": false,
                "record_id": "ba-01-n-15170"
            }
        ],
        "value": 1.131698355131417e-06
    },
    "Ar38": {
        "error": 2.3475750496523744e-07,
        "error_type": "",
        "fit": "previous",
        "references": [
            {
                "exclude": false,
                "record_id": "ba-01-n-15170"
            }
        ],
        "value": -9.772967632238456e-08
    },
    "Ar39": {
        "error": 2.0737459722990116e-07,
        "error_type": "",
        "fit": "previous",
        "references": [
            {
                "exclude": false,
                "record_id": "ba-01-n-15170"
            }
        ],
        "value": 6.992292868977378e-07
    },
    "Ar40": {
        "error": 1.1806078278786437e-06,
        "error_type": "",
        "fit": "previous",
        "references": [
            {
                "exclude": false,
                "record_id": "ba-01-n-15170"
            }
        ],
        "value": 3.123315180322558e-05
    }
}