{
    "baselines": [
        {
            "blob": "QkjMkLe9fOVCcW0wt8AGIUKM/h+3pvkT",
            "detector": "H3"
        },
        {
            "blob": "QkjMkLhRNqBCcW0wuFP9q0KM/h+4QxsP",
            "detector": "H1"
        },
        {
            "blob": "QkjMkLi1WgxCcW0wuLW3W0KM/h+4r2P7",
            "detector": "L1"
        },
        {
            "blob": "QkjMkLelHgRCcW0wt6tkgkKM/h+3lgTz",
            "detector": "L3"
        },
        {
            "blob": "QkjMkLwCfwJCcW0wvAJ2VUKM/h+8Am/0",
            "detector": "L5"
        }
    ],
    "commit": "2ddfb96f1e2020588a5f33e9c9d90a02a5ef9f45",
    "encoding": "base64",
    "format": ">ff",
    "signals": [
        {
            "blob": "QborpT4y4XdCCTxZPjIhpA==",
            "detector": "H3",
            "isotope": "Ar40"
        },
        {
            "blob": "QborpbgTU45CCTxZt94/HA==",
            "detector": "H1",
            "isotope": "Ar39"
        },
        {
            "blob": "QborpTe6VDhCCTxZN7nJgw==",
            "detector": "L1",
            "isotope": "Ar38"
        },
        {
            "blob": "QborpbeKgqtCCTxZt6Nb5Q==",
            "detector": "L3",
            "isotope": "Ar37"
        },
        {
            "blob": "QborpbvyjgVCCTxZu/KJJg==",
            "detector": "L5",
            "isotope": "Ar36"
        }
    ],
    "sniffs": [
        {
            "blob": null,
            "detector": "H3",
            "isotope": "Ar40"
        },
        {
            "blob": null,
            "detector": "H1",
            "isotope": "Ar39"
        },
        {
            "blob": null,
            "detector": "L1",
            "isotope": "Ar38"
        },
        {
            "blob": null,
            "detector": "L3",
            "isotope": "Ar37"
        },
        {
            "blob": null,
            "detector": "L5",
            "isotope": "Ar36"
        }
    ]
}