{
    "Ar36": {
        "error": 9.066790994125218e-09,
        "error_type": "",
        "fit": "previous",
        "references": [
            {
                "exclude": false,
                "record_id": "ba-01-n-14824"
            }
        ],
        "value": 2.5811627406926265e-07
    },
    "Ar37": {
        "error": 3.4050966544760495e-07,
        "error_type": "",
        "fit": "previous",
        "references": [
            {
                "exclude": false,
                "record_id": "ba-01-n-14824"
            }
        ],
        "value": 3.8162495467728116e-07
    },
    "Ar38": {
        "error": 2.2257172102929022e-07,
        "error_type": "",
        "fit": "previous",
        "references": [
            {
                "exclude": false,
                "record_id": "ba-01-n-14824"
            }
        ],
        "value": 1.857344235524491e-07
    },
    "Ar39": {
        "error": 3.639140296598399e-07,
        "error_type": "",
        "fit": "previous",
        "references": [
            {
                "exclude": false,
                "record_id": "ba-01-n-14824"
            }
        ],
        "value": -1.0016180401007995e-07
    },
    "Ar40": {
        "error": 8.918756771828055e-07,
        "error_type": "",
        "fit": "previous",
        "references": [
            {
                "exclude": false,
                "record_id": "ba-01-n-14824"
            }
        ],
        "value": 6.886971855387026e-05
    }
}