{
    "Ar36": {
        "error": 2.586108269294317e-07,
        "error_type": "",
        "fit": "previous",
        "references": [
            {
                "exclude": false,
                "record_id": "ba-01-n-14984"
            }
        ],
        "value": -1.0929622263240735e-06
    },
    "Ar37": {
        "error": 2.584259936611723e-07,
        "error_type": "",
        "fit": "previous",
        "references": [
            {
                "exclude": false,
                "record_id": "ba-01-n-14984"
            }
        ],
        "value": 6.407954886284438e-07
    },
    "Ar38": {
        "error": 2.2015683964992807e-07,
        "error_type": "",
        "fit": "previous",
        "references": [
            {
                "exclude": false,
                "record_id": "ba-01-n-14984"
            }
        ],
        "value": -1.6733468204230707e-07
    },
    "Ar39": {
        "error": 2.545981368869423e-07,
        "error_type": "",
        "fit": "previous",
        "references": [
            {
                "exclude": false,
                "record_id": "ba-01-n-14984"
            }
        ],
        "value": 6.925029585750156e-07
    },
    "Ar40": {
        "error": 1.1079206572968034e-06,
        "error_type": "",
        "fit": "previous",
        "references": [
            {
                "exclude": false,
                "record_id": "ba-01-n-14984"
            }
        ],
        "value": 1.9726283329918928e-06
    }
}