{
    "Ar36": {
        "error": 5.76772507556139e-07,
        "error_type": "SEM",
        "filter_outliers_dict": {
            "filter_outliers": true,
            "iterations": 1,
            "std_devs": 2
        },
        "fit": "linear",
        "value": -0.007395539545669384
    },
    "Ar37": {
        "error": 2.90246515876314e-07,
        "error_type": "SEM",
        "filter_outliers_dict": {
            "filter_outliers": true,
            "iterations": 1,
            "std_devs": 2
        },
        "fit": "linear",
        "value": -1.775996293901372e-05
    },
    "Ar38": {
        "error": 3.3915140461957546e-07,
        "error_type": "SEM",
        "filter_outliers_dict": {
            "filter_outliers": true,
            "iterations": 1,
            "std_devs": 2
        },
        "fit": "linear",
        "value": 2.3865092599472004e-05
    },
    "Ar39": {
        "error": 1.6592775049903074e-06,
        "error_type": "SEM",
        "filter_outliers_dict": {
            "filter_outliers": true,
            "iterations": 1,
            "std_devs": 2
        },
        "fit": "linear",
        "value": -4.6201253870761036e-05
    },
    "Ar40": {
        "error": 3.7510150907814285e-05,
        "error_type": "SEM",
        "filter_outliers_dict": {
            "filter_outliers": true,
            "iterations": 1,
            "std_devs": 2
        },
        "fit": "parabolic",
        "value": 0.1769084595516427
    }
}