{
    "Ar36": {
        "error": 2.7004464277466177e-07,
        "error_type": "",
        "fit": "previous",
        "references": [
            {
                "exclude": false,
                "record_id": "ba-01-n-14546"
            }
        ],
        "value": -7.772023896211039e-07
    },
    "Ar37": {
        "error": 1.5233787169416526e-07,
        "error_type": "",
        "fit": "previous",
        "references": [
            {
                "exclude": false,
                "record_id": "ba-01-n-14546"
            }
        ],
        "value": 7.401675048004724e-07
    },
    "Ar38": {
        "error": 2.1484514863507703e-07,
        "error_type": "",
        "fit": "previous",
        "references": [
            {
                "exclude": false,
                "record_id": "ba-01-n-14546"
            }
        ],
        "value": 4.7430762647633086e-08
    },
    "Ar39": {
        "error": 1.9622853130387187e-07,
        "error_type": "",
        "fit": "previous",
        "references": [
            {
                "exclude": false,
                "record_id": "ba-01-n-14546"
            }
        ],
        "value": 7.47070385646196e-07
    },
    "Ar40": {
        "error": 9.078619367686771e-07,
        "error_type": "",
        "fit": "previous",
        "references": [
            {
                "exclude": false,
                "record_id": "ba-01-n-14546"
            }
        ],
        "value": 5.722526955681995e-06
    }
}